README.md
setup.py
minitk/__init__.py
minitk/control_panel.py
minitk.egg-info/PKG-INFO
minitk.egg-info/SOURCES.txt
minitk.egg-info/dependency_links.txt
minitk.egg-info/requires.txt
minitk.egg-info/top_level.txt