Metadata-Version: 2.1
Name: minitk
Version: 0.7.3
Summary: Minimalist non blocking control panel for parameters
Home-page: https://gitlab.com/jldez/minitk
Author: Jean-Luc Déziel
Author-email: jluc1011@hotmail.com
